{
  "annotations": {
    "list": [
      {
        "builtIn": 1,
        "datasource": {
          "type": "grafana",
          "uid": "-- Grafana --"
        },
        "enable": true,
        "hide": true,
        "iconColor": "rgba(0, 211, 255, 1)",
        "name": "Annotations & Alerts",
        "type": "dashboard"
      }
    ]
  },
  "editable": true,
  "fiscalYearStartMonth": 0,
  "graphTooltip": 0,
  "id": null,
  "links": [],
  "liveNow": false,
  "panels": [
    {
      "datasource": {
        "type": "loki",
        "uid": "${ds_loki}"
      },
      "fieldConfig": {
        "defaults": {
          "color": {
            "mode": "thresholds"
          },
          "mappings": [],
          "thresholds": {
            "mode": "absolute",
            "steps": [
              {
                "color": "green",
                "value": null
              },
              {
                "color": "orange",
                "value": 1000
              },
              {
                "color": "red",
                "value": 5000
              }
            ]
          },
          "unit": "short"
        },
        "overrides": []
      },
      "gridPos": {
        "h": 5,
        "w": 6,
        "x": 0,
        "y": 0
      },
      "id": 1,
      "options": {
        "colorMode": "background",
        "graphMode": "none",
        "justifyMode": "auto",
        "orientation": "auto",
        "reduceOptions": {
          "calcs": [
            "lastNotNull"
          ],
          "fields": "",
          "values": false
        },
        "textMode": "auto"
      },
      "targets": [
        {
          "datasource": {
            "type": "loki",
            "uid": "${ds_loki}"
          },
          "editorMode": "code",
          "expr": "sum(count_over_time({service=~\"$service\", level=~\"$level\", module=~\"$module\", http_method=~\"$http_method\"}[$__range]))",
          "queryType": "range",
          "refId": "A"
        }
      ],
      "title": "Total Logs",
      "type": "stat"
    },
    {
      "datasource": {
        "type": "loki",
        "uid": "${ds_loki}"
      },
      "fieldConfig": {
        "defaults": {
          "color": {
            "mode": "thresholds"
          },
          "mappings": [],
          "thresholds": {
            "mode": "absolute",
            "steps": [
              {
                "color": "green",
                "value": null
              },
              {
                "color": "orange",
                "value": 10
              },
              {
                "color": "red",
                "value": 100
              }
            ]
          },
          "unit": "short"
        },
        "overrides": []
      },
      "gridPos": {
        "h": 5,
        "w": 6,
        "x": 6,
        "y": 0
      },
      "id": 2,
      "options": {
        "colorMode": "background",
        "graphMode": "none",
        "justifyMode": "auto",
        "orientation": "auto",
        "reduceOptions": {
          "calcs": [
            "lastNotNull"
          ],
          "fields": "",
          "values": false
        },
        "textMode": "auto"
      },
      "targets": [
        {
          "datasource": {
            "type": "loki",
            "uid": "${ds_loki}"
          },
          "editorMode": "code",
          "expr": "sum(count_over_time({service=~\"$service\", level=~\"ERROR|CRITICAL\", module=~\"$module\", http_method=~\"$http_method\"}[$__range]))",
          "queryType": "range",
          "refId": "A"
        }
      ],
      "title": "Error Logs",
      "type": "stat"
    },
    {
      "datasource": {
        "type": "loki",
        "uid": "${ds_loki}"
      },
      "fieldConfig": {
        "defaults": {
          "color": {
            "mode": "thresholds"
          },
          "mappings": [],
          "max": 100,
          "min": 0,
          "thresholds": {
            "mode": "absolute",
            "steps": [
              {
                "color": "green",
                "value": null
              },
              {
                "color": "orange",
                "value": 1
              },
              {
                "color": "red",
                "value": 5
              }
            ]
          },
          "unit": "percent"
        },
        "overrides": []
      },
      "gridPos": {
        "h": 5,
        "w": 6,
        "x": 12,
        "y": 0
      },
      "id": 3,
      "options": {
        "colorMode": "background",
        "graphMode": "none",
        "justifyMode": "auto",
        "orientation": "auto",
        "reduceOptions": {
          "calcs": [
            "lastNotNull"
          ],
          "fields": "",
          "values": false
        },
        "textMode": "auto"
      },
      "targets": [
        {
          "datasource": {
            "type": "loki",
            "uid": "${ds_loki}"
          },
          "editorMode": "code",
          "expr": "sum(count_over_time({service=~\"$service\", level=~\"ERROR|CRITICAL\", module=~\"$module\", http_method=~\"$http_method\"}[$__range]))",
          "queryType": "range",
          "refId": "A"
        },
        {
          "datasource": {
            "type": "loki",
            "uid": "${ds_loki}"
          },
          "editorMode": "code",
          "expr": "sum(count_over_time({service=~\"$service\", level=~\"$level\", module=~\"$module\", http_method=~\"$http_method\"}[$__range]))",
          "queryType": "range",
          "refId": "B"
        },
        {
          "datasource": {
            "type": "__expr__",
            "uid": "__expr__"
          },
          "expression": "($A / clamp_min($B, 1)) * 100",
          "refId": "C",
          "type": "math"
        }
      ],
      "title": "Error Rate",
      "type": "stat"
    },
    {
      "datasource": {
        "type": "loki",
        "uid": "${ds_loki}"
      },
      "fieldConfig": {
        "defaults": {
          "color": {
            "mode": "thresholds"
          },
          "mappings": [],
          "thresholds": {
            "mode": "absolute",
            "steps": [
              {
                "color": "green",
                "value": null
              },
              {
                "color": "red",
                "value": 0.5
              }
            ]
          },
          "unit": "logs"
        },
        "overrides": []
      },
      "gridPos": {
        "h": 5,
        "w": 6,
        "x": 18,
        "y": 0
      },
      "id": 4,
      "options": {
        "colorMode": "background",
        "graphMode": "none",
        "justifyMode": "auto",
        "orientation": "auto",
        "reduceOptions": {
          "calcs": [
            "lastNotNull"
          ],
          "fields": "",
          "values": false
        },
        "textMode": "auto"
      },
      "targets": [
        {
          "datasource": {
            "type": "loki",
            "uid": "${ds_loki}"
          },
          "editorMode": "code",
          "expr": "sum(rate({service=~\"$service\", level=~\"$level\", module=~\"$module\", http_method=~\"$http_method\"}[5m]))",
          "queryType": "range",
          "refId": "A"
        }
      ],
      "title": "Current Log Throughput (logs/s)",
      "type": "stat"
    },
    {
      "datasource": {
        "type": "loki",
        "uid": "${ds_loki}"
      },
      "fieldConfig": {
        "defaults": {
          "color": {
            "mode": "palette-classic"
          },
          "custom": {
            "axisBorderShow": false,
            "axisCenteredZero": false,
            "axisColorMode": "text",
            "axisLabel": "",
            "axisPlacement": "auto",
            "barAlignment": 0,
            "drawStyle": "line",
            "fillOpacity": 25,
            "gradientMode": "none",
            "hideFrom": {
              "legend": false,
              "tooltip": false,
              "viz": false
            },
            "insertNulls": false,
            "lineInterpolation": "linear",
            "lineWidth": 1,
            "pointSize": 3,
            "scaleDistribution": {
              "type": "linear"
            },
            "showPoints": "never",
            "spanNulls": false,
            "stacking": {
              "group": "A",
              "mode": "normal"
            },
            "thresholdsStyle": {
              "mode": "off"
            }
          },
          "mappings": [],
          "thresholds": {
            "mode": "absolute",
            "steps": [
              {
                "color": "green",
                "value": null
              },
              {
                "color": "red",
                "value": 80
              }
            ]
          },
          "unit": "short"
        },
        "overrides": []
      },
      "gridPos": {
        "h": 8,
        "w": 12,
        "x": 0,
        "y": 5
      },
      "id": 5,
      "options": {
        "legend": {
          "calcs": [
            "lastNotNull",
            "max",
            "sum"
          ],
          "displayMode": "table",
          "placement": "bottom",
          "showLegend": true
        },
        "tooltip": {
          "mode": "multi",
          "sort": "none"
        }
      },
      "targets": [
        {
          "datasource": {
            "type": "loki",
            "uid": "${ds_loki}"
          },
          "editorMode": "code",
          "expr": "sum by (level) (count_over_time({service=~\"$service\", level=~\"$level\", module=~\"$module\", http_method=~\"$http_method\"}[$__interval]))",
          "queryType": "range",
          "refId": "A"
        }
      ],
      "title": "Logs Over Time by Level",
      "type": "timeseries"
    },
    {
      "datasource": {
        "type": "loki",
        "uid": "${ds_loki}"
      },
      "fieldConfig": {
        "defaults": {
          "color": {
            "mode": "palette-classic"
          },
          "custom": {
            "axisBorderShow": false,
            "axisCenteredZero": false,
            "axisColorMode": "text",
            "axisLabel": "",
            "axisPlacement": "auto",
            "barAlignment": 0,
            "drawStyle": "line",
            "fillOpacity": 25,
            "gradientMode": "none",
            "hideFrom": {
              "legend": false,
              "tooltip": false,
              "viz": false
            },
            "insertNulls": false,
            "lineInterpolation": "linear",
            "lineWidth": 1,
            "pointSize": 3,
            "scaleDistribution": {
              "type": "linear"
            },
            "showPoints": "never",
            "spanNulls": false,
            "stacking": {
              "group": "A",
              "mode": "normal"
            },
            "thresholdsStyle": {
              "mode": "off"
            }
          },
          "mappings": [],
          "thresholds": {
            "mode": "absolute",
            "steps": [
              {
                "color": "green",
                "value": null
              },
              {
                "color": "red",
                "value": 80
              }
            ]
          },
          "unit": "short"
        },
        "overrides": []
      },
      "gridPos": {
        "h": 8,
        "w": 12,
        "x": 12,
        "y": 5
      },
      "id": 6,
      "options": {
        "legend": {
          "calcs": [
            "lastNotNull",
            "max",
            "sum"
          ],
          "displayMode": "table",
          "placement": "bottom",
          "showLegend": true
        },
        "tooltip": {
          "mode": "multi",
          "sort": "none"
        }
      },
      "targets": [
        {
          "datasource": {
            "type": "loki",
            "uid": "${ds_loki}"
          },
          "editorMode": "code",
          "expr": "sum by (http_method) (count_over_time({service=~\"$service\", level=~\"$level\", module=~\"$module\", http_method=~\"$http_method\"}[$__interval]))",
          "queryType": "range",
          "refId": "A"
        }
      ],
      "title": "Request Logs Over Time by HTTP Method",
      "type": "timeseries"
    },
    {
      "datasource": {
        "type": "loki",
        "uid": "${ds_loki}"
      },
      "fieldConfig": {
        "defaults": {
          "color": {
            "mode": "palette-classic"
          },
          "custom": {
            "axisCenteredZero": false,
            "axisColorMode": "text",
            "axisLabel": "",
            "axisPlacement": "auto",
            "barAlignment": 0,
            "drawStyle": "bars",
            "fillOpacity": 90,
            "gradientMode": "none",
            "hideFrom": {
              "legend": false,
              "tooltip": false,
              "viz": false
            },
            "lineInterpolation": "linear",
            "lineWidth": 1,
            "pointSize": 5,
            "scaleDistribution": {
              "type": "linear"
            },
            "showPoints": "never",
            "spanNulls": false,
            "stacking": {
              "group": "A",
              "mode": "none"
            },
            "thresholdsStyle": {
              "mode": "off"
            }
          },
          "mappings": [],
          "thresholds": {
            "mode": "absolute",
            "steps": [
              {
                "color": "green",
                "value": null
              },
              {
                "color": "red",
                "value": 80
              }
            ]
          },
          "unit": "short"
        },
        "overrides": []
      },
      "gridPos": {
        "h": 8,
        "w": 12,
        "x": 0,
        "y": 13
      },
      "id": 7,
      "options": {
        "legend": {
          "calcs": [
            "lastNotNull",
            "max",
            "sum"
          ],
          "displayMode": "table",
          "placement": "bottom",
          "showLegend": true
        },
        "tooltip": {
          "mode": "multi",
          "sort": "none"
        }
      },
      "targets": [
        {
          "datasource": {
            "type": "loki",
            "uid": "${ds_loki}"
          },
          "editorMode": "code",
          "expr": "sum by (service) (count_over_time({service=~\"$service\", level=~\"$level\", module=~\"$module\", http_method=~\"$http_method\"}[$__range]))",
          "queryType": "range",
          "refId": "A"
        }
      ],
      "title": "Log Volume by Service",
      "type": "timeseries"
    },
    {
      "datasource": {
        "type": "loki",
        "uid": "${ds_loki}"
      },
      "fieldConfig": {
        "defaults": {
          "color": {
            "mode": "palette-classic"
          },
          "custom": {
            "align": "auto",
            "cellOptions": {
              "type": "auto"
            },
            "inspect": false
          },
          "mappings": [],
          "thresholds": {
            "mode": "absolute",
            "steps": [
              {
                "color": "green",
                "value": null
              },
              {
                "color": "red",
                "value": 80
              }
            ]
          }
        },
        "overrides": []
      },
      "gridPos": {
        "h": 8,
        "w": 12,
        "x": 12,
        "y": 13
      },
      "id": 8,
      "options": {
        "footer": {
          "countRows": false,
          "fields": "",
          "reducer": [
            "sum"
          ],
          "show": false
        },
        "showHeader": true,
        "sortBy": [
          {
            "desc": true,
            "displayName": "Value"
          }
        ]
      },
      "targets": [
        {
          "datasource": {
            "type": "loki",
            "uid": "${ds_loki}"
          },
          "editorMode": "code",
          "expr": "topk(10, sum by (module) (count_over_time({service=~\"$service\", level=~\"$level\", module=~\"$module\", http_method=~\"$http_method\"}[$__range])))",
          "queryType": "range",
          "refId": "A"
        }
      ],
      "title": "Top Modules by Log Count",
      "transformations": [
        {
          "id": "reduce",
          "options": {
            "includeTimeField": false,
            "labelsToFields": true,
            "mode": "seriesToRows",
            "reducers": [
              "lastNotNull"
            ]
          }
        }
      ],
      "type": "table"
    },
    {
      "datasource": {
        "type": "loki",
        "uid": "${ds_loki}"
      },
      "gridPos": {
        "h": 8,
        "w": 12,
        "x": 0,
        "y": 21
      },
      "id": 9,
      "options": {
        "dedupStrategy": "none",
        "enableLogDetails": true,
        "prettifyLogMessage": false,
        "showCommonLabels": false,
        "showLabels": true,
        "showTime": true,
        "sortOrder": "Descending",
        "wrapLogMessage": true
      },
      "targets": [
        {
          "datasource": {
            "type": "loki",
            "uid": "${ds_loki}"
          },
          "editorMode": "code",
          "expr": "{service=~\"$service\", level=~\"ERROR|CRITICAL\", module=~\"$module\", http_method=~\"$http_method\"}",
          "queryType": "range",
          "refId": "A"
        }
      ],
      "title": "Recent Error Logs",
      "type": "logs"
    },
    {
      "datasource": {
        "type": "loki",
        "uid": "${ds_loki}"
      },
      "gridPos": {
        "h": 8,
        "w": 12,
        "x": 12,
        "y": 21
      },
      "id": 10,
      "options": {
        "dedupStrategy": "none",
        "enableLogDetails": true,
        "prettifyLogMessage": false,
        "showCommonLabels": false,
        "showLabels": true,
        "showTime": true,
        "sortOrder": "Descending",
        "wrapLogMessage": true
      },
      "targets": [
        {
          "datasource": {
            "type": "loki",
            "uid": "${ds_loki}"
          },
          "editorMode": "code",
          "expr": "{service=~\"$service\", level=~\"$level\", module=~\"$module\", http_method=~\"$http_method\"}",
          "queryType": "range",
          "refId": "A"
        }
      ],
      "title": "Live Request Logs",
      "type": "logs"
    }
  ],
  "refresh": "10s",
  "schemaVersion": 41,
  "style": "dark",
  "tags": [
    "loki",
    "logging",
    "kidsmind",
    "api"
  ],
  "templating": {
    "list": [
      {
        "current": {
          "selected": true,
          "text": "Loki",
          "value": "Loki"
        },
        "hide": 0,
        "includeAll": false,
        "label": "Datasource",
        "multi": false,
        "name": "ds_loki",
        "options": [],
        "query": "loki",
        "refresh": 1,
        "regex": "",
        "skipUrlSync": false,
        "type": "datasource"
      },
      {
        "allValue": ".+",
        "current": {
          "selected": true,
          "text": "All",
          "value": ".+"
        },
        "datasource": {
          "type": "loki",
          "uid": "${ds_loki}"
        },
        "definition": "label_values({service=~\".+\"}, service)",
        "hide": 0,
        "includeAll": true,
        "label": "Service",
        "multi": true,
        "name": "service",
        "options": [],
        "query": {
          "label": "service",
          "refId": "LokiVariableQueryEditor-Service",
          "stream": "{service=~\".+\"}",
          "type": 1
        },
        "refresh": 2,
        "regex": "",
        "skipUrlSync": false,
        "sort": 1,
        "type": "query"
      },
      {
        "allValue": ".*",
        "current": {
          "selected": true,
          "text": "All",
          "value": ".*"
        },
        "datasource": {
          "type": "loki",
          "uid": "${ds_loki}"
        },
        "definition": "label_values({service=~\"$service\"}, level)",
        "hide": 0,
        "includeAll": true,
        "label": "Level",
        "multi": true,
        "name": "level",
        "options": [],
        "query": {
          "label": "level",
          "refId": "LokiVariableQueryEditor-Level",
          "stream": "{service=~\"$service\"}",
          "type": 1
        },
        "refresh": 2,
        "regex": "",
        "skipUrlSync": false,
        "sort": 1,
        "type": "query"
      },
      {
        "allValue": ".*",
        "current": {
          "selected": true,
          "text": "All",
          "value": ".*"
        },
        "datasource": {
          "type": "loki",
          "uid": "${ds_loki}"
        },
        "definition": "label_values({service=~\"$service\"}, module)",
        "hide": 0,
        "includeAll": true,
        "label": "Module",
        "multi": true,
        "name": "module",
        "options": [],
        "query": {
          "label": "module",
          "refId": "LokiVariableQueryEditor-Module",
          "stream": "{service=~\"$service\"}",
          "type": 1
        },
        "refresh": 2,
        "regex": "",
        "skipUrlSync": false,
        "sort": 1,
        "type": "query"
      },
      {
        "allValue": ".*",
        "current": {
          "selected": true,
          "text": "All",
          "value": ".*"
        },
        "datasource": {
          "type": "loki",
          "uid": "${ds_loki}"
        },
        "definition": "label_values({service=~\"$service\"}, http_method)",
        "hide": 0,
        "includeAll": true,
        "label": "HTTP Method",
        "multi": true,
        "name": "http_method",
        "options": [],
        "query": {
          "label": "http_method",
          "refId": "LokiVariableQueryEditor-Method",
          "stream": "{service=~\"$service\"}",
          "type": 1
        },
        "refresh": 2,
        "regex": "",
        "skipUrlSync": false,
        "sort": 1,
        "type": "query"
      }
    ]
  },
  "time": {
    "from": "now-6h",
    "to": "now"
  },
  "timepicker": {},
  "timezone": "",
  "title": "KidsMind - Logging Overview",
  "uid": "kidsmind-logs-overview",
  "version": 1,
  "weekStart": ""
}
